HIT_network/__init__.py
HIT_network/draw_networks.py
HIT_network/random_networks.py
HIT_network/read_txt_networks.py
HIT_network/scale_of_network.py
HIT_networks-0.0.2.dist-info/METADATA
HIT_networks-0.0.2.dist-info/WHEEL
HIT_networks-0.0.2.dist-info/top_level.txt
HIT_networks-0.0.2.dist-info/RECORD
