Metadata-Version: 2.1
Name: HIT-networks
Version: 0.0.2
Summary: This is an integrated shortcut network related programming toolkit, the content is still in the development stage
Home-page: https://github.com/656756130/Network_basementlearning
Author: Jinyan
Author-email: duanjinyan8866@outlook.com
License: MIT-0
Requires-Python: >=3.5
Requires-Dist: numpy
Requires-Dist: matplotlib
Requires-Dist: networkx
